vid2captionsai/__init__.py
vid2captionsai/__main__.py
vid2captionsai/vid2captionsai.py
vid2captionsai-1.0.3.dist-info/LICENSE.txt
vid2captionsai-1.0.3.dist-info/METADATA
vid2captionsai-1.0.3.dist-info/WHEEL
vid2captionsai-1.0.3.dist-info/entry_points.txt
vid2captionsai-1.0.3.dist-info/top_level.txt
vid2captionsai-1.0.3.dist-info/RECORD
