Metadata-Version: 2.1
Name: vid2captionsai
Version: 1.0.3
Summary: Tool for preparing videos for use with https://www.captions.ai/
Home-page: https://pypi.org/project/vid2captionsai/
Author: Adam Twardoch
Author-email: adam+github@twardoch.com
License: Apache-2.0
Project-URL: Source, https://github.com/twardoch/vid2captionsai
Platform: any
Classifier: Development Status :: 4 - Beta
Classifier: Programming Language :: Python
License-File: LICENSE.txt
Requires-Dist: static-ffmpeg >=2.5
Requires-Dist: fire >=0.5.0
Provides-Extra: testing
Requires-Dist: setuptools ; extra == 'testing'
Requires-Dist: pytest ; extra == 'testing'
Requires-Dist: pytest-cov ; extra == 'testing'
